devtools_image_base64/__init__.py
devtools_image_base64-1.0.1.dist-info/METADATA
devtools_image_base64-1.0.1.dist-info/WHEEL
devtools_image_base64-1.0.1.dist-info/top_level.txt
devtools_image_base64-1.0.1.dist-info/RECORD
