Metadata-Version: 2.1
Name: devtools-image-base64
Version: 1.0.1
Summary: Image to Base64 converter
Home-page: https://devtools.at/tools/image-to-base64
Author: DevTools.at
Author-email: hello@devtools.at
Project-URL: Homepage, https://devtools.at/tools/image-to-base64
Project-URL: Repository, https://github.com/devtools-at/image-to-base64
Classifier: Development Status :: 4 - Beta
Classifier: Intended Audience :: Developers
Classifier: License :: OSI Approved :: MIT License
Classifier: Programming Language :: Python :: 3
Requires-Python: >=3.8
